flash_attn_jax/__init__.py
flash_attn_jax/flash.py
flash_attn_jax/flash_bwd.py
flash_attn_jax/flash_fwd.py
flash_attn_jax/flash_hlo.py
flash_attn_jax/flash_sharding.py
flash_attn_jax/ring_attention.py
flash_attn_jax/util.py
flash_attn_jax/varlen.py
flash_attn_jax/varlen_bwd.py
flash_attn_jax/varlen_fwd.py
flash_attn_jax_lib/flash_api.cpython-311-x86_64-linux-gnu.so
flash_attn_jax-0.5.4.dist-info/METADATA
flash_attn_jax-0.5.4.dist-info/WHEEL
flash_attn_jax-0.5.4.dist-info/RECORD
flash_attn_jax-0.5.4.dist-info/licenses/AUTHORS
flash_attn_jax-0.5.4.dist-info/licenses/LICENSE
