Metadata-Version: 2.2
Name: flash_attn_jax
Version: 0.5.4
Summary: Flash Attention port for JAX
Author-Email: Tri Dao <tri@tridao.me>, Emily Shepperd <em@zlkj.in>
License: BSD-3-Clause
Classifier: Programming Language :: Python :: 3
Classifier: License :: OSI Approved :: BSD License
Classifier: Operating System :: Unix
Project-URL: Homepage, https://github.com/nshepperd/flash_attn_jax
Requires-Python: >=3.11
Requires-Dist: nanobind>=2.0.0
Requires-Dist: jax<0.9.0,>=0.5.0
